[
    {
        "campaign_id": 100,
        "campaign_name": "【7.5周年】強化大成功率アップキャンペーン",
        "campaign_type": 2,
        "campaign_value": 40000,
        "live_id": 0,
        "stage_id": 0,
        "start_date": 1747288800,
        "end_date": 1751255999,
        "resource_id": 0,
        "description": ""
    },
    {
        "campaign_id": 101,
        "campaign_name": "【結成14周年】強化大成功率アップキャンペーン",
        "campaign_type": 2,
        "campaign_value": 40000,
        "live_id": 0,
        "stage_id": 0,
        "start_date": 1755756000,
        "end_date": 1760162399,
        "resource_id": 0,
        "description": ""
    }
]
